mixbag/__init__.py
mixbag/custom_resources.py
mixbag/module_loading.py
mixbag/secrets.py
mixbag-0.0.0a0.dist-info/LICENSE
mixbag-0.0.0a0.dist-info/WHEEL
mixbag-0.0.0a0.dist-info/METADATA
mixbag-0.0.0a0.dist-info/RECORD
